pytorch_skipthoughts-0.4.4.dist-info/DESCRIPTION.rst
pytorch_skipthoughts-0.4.4.dist-info/METADATA
pytorch_skipthoughts-0.4.4.dist-info/RECORD
pytorch_skipthoughts-0.4.4.dist-info/WHEEL
pytorch_skipthoughts-0.4.4.dist-info/metadata.json
pytorch_skipthoughts-0.4.4.dist-info/top_level.txt
torchst/__init__.py
torchst/model.py
torchst/train.py
torchst/vectorize.py
torchst/wordembed.py
