Metadata-Version: 2.0
Name: pytorch-skipthoughts
Version: 0.4.4
Summary: Multi-GPU Customizable Implementation of Skip-Thoughts in PyTorch
Home-page: https://github.com/kaniblu/pytorch-skipthoughts
Author: Kang Min Yoo
Author-email: k@nib.lu
License: MIT
Keywords: pytorch skip-thoughts multi-gpu gpu cuda deep learning nlp
Platform: UNKNOWN
Classifier: Development Status :: 3 - Alpha
Classifier: Intended Audience :: Developers
Classifier: Programming Language :: Python :: 3
Requires-Dist: pyaap
Requires-Dist: pytorch-sru
Requires-Dist: pytorch-text-utils
Requires-Dist: tqdm
Requires-Dist: visdom-pooled
